<?xml version="1.0" encoding="UTF-8" standalone="yes"?>
<electionDefinition>
    <electionId>HSR2013</electionId>
    <title>Präsidentschaftswahlen Studentenrat</title>
    <keyLength>256</keyLength>
    <mixerId>Gian</mixerId>
    <mixerId>Ueli</mixerId>
    <mixerId>Hans</mixerId>
    <mixerId>Peter</mixerId>
    <mixerId>Giachen</mixerId>
    <tallierId>Sven</tallierId>
    <tallierId>Beat</tallierId>
    <tallierId>Bruno</tallierId>
    <tallierId>Clemens</tallierId>
    <votingPhaseBegin>2013-01-01T07:00:00.000Z</votingPhaseBegin>
    <votingPhaseEnd>2013-01-01T11:00:00.000Z</votingPhaseEnd>
    <signature>
        <signerId>Gian Poltéra</signerId>
        <timestamp>2014-01-11T01:33:28.000Z</timestamp>
        <value>1132229499443898182364513361536007859642425179009039168812920101945559122183167654058592425412740260186415647817536636094119446977627110311626686080667111</value>
    </signature>
</electionDefinition>

